dirty_validators/__init__.py
dirty_validators/async_complex.py
dirty_validators/basic.py
dirty_validators/complex.py
dirty_validators-0.5.4.dist-info/LICENSE
dirty_validators-0.5.4.dist-info/METADATA
dirty_validators-0.5.4.dist-info/WHEEL
dirty_validators-0.5.4.dist-info/pbr.json
dirty_validators-0.5.4.dist-info/top_level.txt
dirty_validators-0.5.4.dist-info/zip-safe
dirty_validators-0.5.4.dist-info/RECORD
