Metadata-Version: 2.1
Name: dirty-validators
Version: 0.5.4
Summary: Validate library for python 3
Home-page: https://github.com/alfred82santa/dirty-validators
Author: alfred82santa
Author-email: alfred82santa@gmail.com
License: UNKNOWN
Platform: UNKNOWN
